pycheckmate.py
pycheckmate-1.0.1.dist-info/LICENSE
pycheckmate-1.0.1.dist-info/METADATA
pycheckmate-1.0.1.dist-info/WHEEL
pycheckmate-1.0.1.dist-info/top_level.txt
pycheckmate-1.0.1.dist-info/RECORD
