Metadata-Version: 2.1
Name: pycheckmate
Version: 1.0.1
Summary: src is a library designed to analyze Python code for various properties, focusing primarily on the evaluation of code authored by programming novices
Home-page: https://git.rwth-aachen.de/learntech-lufgi9/public/pycheckmate
Author: Annabell Brocker,The Learning Technologies Research Group,RWTH Aachen University
Author-email: a.brocker@cs.rwth-aachen.de
License: MIT
Platform: any
Classifier: Programming Language :: Python :: 3
Classifier: License :: OSI Approved :: MIT License
Classifier: Operating System :: OS Independent
Requires-Python: >=3.9
License-File: LICENSE
